quanti_fret/__init__.py
quanti_fret/algo/__init__.py
quanti_fret/algo/background/__init__.py
quanti_fret/algo/background/background.py
quanti_fret/algo/background/disabled.py
quanti_fret/algo/background/engine.py
quanti_fret/algo/background/fixed.py
quanti_fret/algo/background/mask.py
quanti_fret/algo/background/mode.py
quanti_fret/algo/background/percentile.py
quanti_fret/algo/fret.py
quanti_fret/algo/gamma/__init__.py
quanti_fret/algo/gamma/bt.py
quanti_fret/algo/gamma/calculator.py
quanti_fret/algo/gamma/de.py
quanti_fret/algo/matrix_functions.py
quanti_fret/algo/plot.py
quanti_fret/algo/xm.py
quanti_fret/apps/__init__.py
quanti_fret/apps/app_default_path.py
quanti_fret/apps/cli/__init__.py
quanti_fret/apps/cli/controller.py
quanti_fret/apps/cli/view/__init__.py
quanti_fret/apps/cli/view/calculation_view.py
quanti_fret/apps/cli/view/cli_view.py
quanti_fret/apps/cli/view/printers.py
quanti_fret/apps/cli/view/series_view.py
quanti_fret/apps/cli/view/stage_view.py
quanti_fret/apps/gui/__init__.py
quanti_fret/apps/gui/config/__init__.py
quanti_fret/apps/gui/config/calibration.py
quanti_fret/apps/gui/config/config.py
quanti_fret/apps/gui/config/fret.py
quanti_fret/apps/gui/io_gui_manager.py
quanti_fret/apps/gui/path.py
quanti_fret/apps/gui/phases/__init__.py
quanti_fret/apps/gui/phases/calibration.py
quanti_fret/apps/gui/phases/fret.py
quanti_fret/apps/gui/phases/phase.py
quanti_fret/apps/gui/popup/__init__.py
quanti_fret/apps/gui/popup/figure.py
quanti_fret/apps/gui/popup/manager.py
quanti_fret/apps/gui/popup/napari.py
quanti_fret/apps/gui/popup/standalone.py
quanti_fret/apps/gui/runner.py
quanti_fret/apps/gui/series/__init__.py
quanti_fret/apps/gui/series/regex.py
quanti_fret/apps/gui/series/single_series_manager.py
quanti_fret/apps/gui/series/triplet_scanner.py
quanti_fret/apps/gui/stages/__init__.py
quanti_fret/apps/gui/stages/background/__init__.py
quanti_fret/apps/gui/stages/background/calibration.py
quanti_fret/apps/gui/stages/background/floating.py
quanti_fret-1.0.0.dist-info/METADATA
quanti_fret-1.0.0.dist-info/WHEEL
quanti_fret-1.0.0.dist-info/entry_points.txt
quanti_fret-1.0.0.dist-info/licenses/LICENSE.txt
quanti_fret-1.0.0.dist-info/RECORD
