Metadata-Version: 2.4
Name: quanti-fret
Version: 1.0.0
Summary: Performs QuanTI-FRET calibration and analysis from 3-channel movies
License-Expression: BSD-3-Clause
License-File: LICENSE.txt
Author: Aurélie Dupont
Author-email: aurelie.dupont@univ-grenoble-alpes.fr
Requires-Python: >=3.10
Classifier: Development Status :: 6 - Mature
Classifier: Framework :: napari
Classifier: Intended Audience :: Science/Research
Classifier: License :: OSI Approved :: BSD License
Classifier: Natural Language :: English
Classifier: Operating System :: OS Independent
Classifier: Programming Language :: Python :: 3
Classifier: Topic :: Scientific/Engineering
Classifier: Topic :: Scientific/Engineering :: Image Processing
Classifier: Topic :: Scientific/Engineering :: Physics
Classifier: Typing :: Typed
Requires-Dist: matplotlib (>=3.10.7,<4.0.0)
Requires-Dist: numpy (>=2.2.6,<3.0.0)
Requires-Dist: pandas (>=2.3.3,<3.0.0)
Requires-Dist: platformdirs (>=4.5.0,<5.0.0)
Requires-Dist: qtpy (>=2.4.3,<3.0.0)
Requires-Dist: scipy (>=1.15.3,<2.0.0)
Requires-Dist: tifffile (>=2025.5.10,<2026.0.0)
Requires-Dist: tqdm (>=4.67.1,<5.0.0)
Project-URL: Changelog, https://gricad-gitlab.univ-grenoble-alpes.fr/liphy/quanti-fret/-/blob/main/CHANGELOG.md?ref_type=heads
Project-URL: Documentation, https://liphy.gricad-pages.univ-grenoble-alpes.fr/quanti-fret/
Project-URL: Homepage, https://liphy-annuaire.univ-grenoble-alpes.fr/pages_personnelles/aurelie_dupont/quantifret/index_quantifret.html
Project-URL: Repository, https://gricad-gitlab.univ-grenoble-alpes.fr/liphy/quanti-fret
Project-URL: Releasenotes, https://gricad-gitlab.univ-grenoble-alpes.fr/liphy/quanti-fret/-/releases
